pytoolbox4dev/__init__.py
pytoolbox4dev/utils/__init__.py
pytoolbox4dev/utils/common_functions.py
pytoolbox4dev-0.0.1.dist-info/METADATA
pytoolbox4dev-0.0.1.dist-info/WHEEL
pytoolbox4dev-0.0.1.dist-info/top_level.txt
pytoolbox4dev-0.0.1.dist-info/RECORD
